Workbook

Sheet Cover
B2: Northwind Analytics — Five-Year Financial Model
B3: Base case · £ · fiscal years ending 31 March
B5: Purpose | C5: Five-year operating model and DCF valuation for FY27 planning.
B6: How to use | C6: Change only the blue cells on the Assumptions sheet; everything else is formula-driven.
B7: Sheets | C7: Assumptions → P&L → Cash Flow → Valuation
B8: Version | C8: v1.0 · 8 October 2026 · Finance
B9: Inputs | C9: Blue text on cream fill
B10: Formulas | C10: Black text
B11: Checks | C11: Valuation!C18 must read OK

Sheet Assumptions
B2: Assumptions
B3: Blue cells are inputs. All other sheets reference this page.
B5: Driver | C5: FY26A | D5: FY27E | E5: FY28E | F5: FY29E | G5: FY30E | H5: Note
B6: Revenue growth | D6: 0.21 | E6: 0.19 | F6: 0.17 | G6: 0.15 | H6: FY26A is actual
B7: Gross margin | C7: 0.731 | D7: 0.738 | E7: 0.745 | F7: 0.75 | G7: 0.755 | H7: Hosting renegotiation
B8: Sales & marketing, % revenue | C8: 0.35 | D8: 0.34 | E8: 0.33 | F8: 0.32 | G8: 0.31
B9: R&D, % revenue | C9: 0.2 | D9: 0.2 | E9: 0.19 | F9: 0.19 | G9: 0.18
B10: G&A, % revenue | C10: 0.098 | D10: 0.094 | E10: 0.09 | F10: 0.087 | G10: 0.085
B11: D&A, % revenue | C11: 0.03 | D11: 0.03 | E11: 0.03 | F11: 0.03 | G11: 0.03
B12: Capex, % revenue | C12: 0.04 | D12: 0.12 | E12: 0.05 | F12: 0.04 | G12: 0.04 | H12: FY27 includes APAC hub
B13: Net working capital, % revenue | C13: 0.08 | D13: 0.08 | E13: 0.08 | F13: 0.08 | G13: 0.08
B14: Tax rate | C14: 0.25 | D14: 0.25 | E14: 0.25 | F14: 0.25 | G14: 0.25 | H14: UK main rate
B16: FY26 revenue (actual), £ | C16: 40100000
B18: Valuation inputs | C18: Value
B19: WACC | C19: 0.11
B20: Terminal growth | C20: 0.03
B21: Net cash at valuation date, £ | C21: 6200000

Sheet P&L
B2: Profit & Loss
B3: £ · all figures formula-driven from Assumptions
B5: £ | C5: FY26A | D5: FY27E | E5: FY28E | F5: FY29E | G5: FY30E
B6: Revenue | C6: =Assumptions!C16 | D6: =C6*(1+Assumptions!D6) | E6: =D6*(1+Assumptions!E6) | F6: =E6*(1+Assumptions!F6) | G6: =F6*(1+Assumptions!G6)
B7: Cost of revenue | C7: =-C6*(1-Assumptions!C7) | D7: =-D6*(1-Assumptions!D7) | E7: =-E6*(1-Assumptions!E7) | F7: =-F6*(1-Assumptions!F7) | G7: =-G6*(1-Assumptions!G7)
B8: Gross profit | C8: =C6+C7 | D8: =D6+D7 | E8: =E6+E7 | F8: =F6+F7 | G8: =G6+G7
B9: Sales & marketing | C9: =-C6*Assumptions!C8 | D9: =-D6*Assumptions!D8 | E9: =-E6*Assumptions!E8 | F9: =-F6*Assumptions!F8 | G9: =-G6*Assumptions!G8
B10: Research & development | C10: =-C6*Assumptions!C9 | D10: =-D6*Assumptions!D9 | E10: =-E6*Assumptions!E9 | F10: =-F6*Assumptions!F9 | G10: =-G6*Assumptions!G9
B11: General & administrative | C11: =-C6*Assumptions!C10 | D11: =-D6*Assumptions!D10 | E11: =-E6*Assumptions!E10 | F11: =-F6*Assumptions!F10 | G11: =-G6*Assumptions!G10
B12: EBITDA | C12: =SUM(C8:C11) | D12: =SUM(D8:D11) | E12: =SUM(E8:E11) | F12: =SUM(F8:F11) | G12: =SUM(G8:G11)
B13: Depreciation & amortisation | C13: =-C6*Assumptions!C11 | D13: =-D6*Assumptions!D11 | E13: =-E6*Assumptions!E11 | F13: =-F6*Assumptions!F11 | G13: =-G6*Assumptions!G11
B14: EBIT | C14: =C12+C13 | D14: =D12+D13 | E14: =E12+E13 | F14: =F12+F13 | G14: =G12+G13
B15: Tax | C15: =-MAX(0,C14)*Assumptions!C14 | D15: =-MAX(0,D14)*Assumptions!D14 | E15: =-MAX(0,E14)*Assumptions!E14 | F15: =-MAX(0,F14)*Assumptions!F14 | G15: =-MAX(0,G14)*Assumptions!G14
B16: Net income | C16: =C14+C15 | D16: =D14+D15 | E16: =E14+E15 | F16: =F14+F15 | G16: =G14+G15
B18: Margins
B19: Revenue growth | D19: =D6/C6-1 | E19: =E6/D6-1 | F19: =F6/E6-1 | G19: =G6/F6-1
B20: Gross margin | C20: =C8/C6 | D20: =D8/D6 | E20: =E8/E6 | F20: =F8/F6 | G20: =G8/G6
B21: EBITDA margin | C21: =C12/C6 | D21: =D12/D6 | E21: =E12/E6 | F21: =F12/F6 | G21: =G12/G6
B22: Net margin | C22: =C16/C6 | D22: =D16/D6 | E22: =E16/E6 | F22: =F16/F6 | G22: =G16/G6

Sheet Cash Flow
B2: Cash Flow
B3: Unlevered free cash flow · £
B5: £ | C5: FY26A | D5: FY27E | E5: FY28E | F5: FY29E | G5: FY30E
B6: EBITDA | C6: ='P&L'!C12 | D6: ='P&L'!D12 | E6: ='P&L'!E12 | F6: ='P&L'!F12 | G6: ='P&L'!G12
B7: Tax on EBIT | C7: ='P&L'!C15 | D7: ='P&L'!D15 | E7: ='P&L'!E15 | F7: ='P&L'!F15 | G7: ='P&L'!G15
B8: Capex | C8: =-'P&L'!C6*Assumptions!C12 | D8: =-'P&L'!D6*Assumptions!D12 | E8: =-'P&L'!E6*Assumptions!E12 | F8: =-'P&L'!F6*Assumptions!F12 | G8: =-'P&L'!G6*Assumptions!G12
B9: Change in net working capital | C9: =0 | D9: =-('P&L'!D6-'P&L'!C6)*Assumptions!D13 | E9: =-('P&L'!E6-'P&L'!D6)*Assumptions!E13 | F9: =-('P&L'!F6-'P&L'!E6)*Assumptions!F13 | G9: =-('P&L'!G6-'P&L'!F6)*Assumptions!G13
B10: Unlevered free cash flow | C10: =SUM(C6:C9) | D10: =SUM(D6:D9) | E10: =SUM(E6:E9) | F10: =SUM(F6:F9) | G10: =SUM(G6:G9)
B12: Discount period (years) | D12: 1 | E12: 2 | F12: 3 | G12: 4
B13: Discount factor | D13: =1/(1+Assumptions!$C$19)^D12 | E13: =1/(1+Assumptions!$C$19)^E12 | F13: =1/(1+Assumptions!$C$19)^F12 | G13: =1/(1+Assumptions!$C$19)^G12
B14: Present value of FCF | D14: =D10*D13 | E14: =E10*E13 | F14: =F10*F13 | G14: =G10*G13

Sheet Valuation
B2: DCF Valuation
B3: Enterprise and equity value · £
B5: Item | C5: Value
B6: Sum of PV of FCF (FY27–FY30) | C6: =SUM('Cash Flow'!D14:G14) | E6: Sensitivity and scenario tabs can be added beside this sheet.
B7: Terminal-year FCF × (1 + g) | C7: ='Cash Flow'!G10*(1+Assumptions!C20)
B8: Terminal value | C8: =C7/(Assumptions!C19-Assumptions!C20)
B9: PV of terminal value | C9: =C8*'Cash Flow'!G13
B10: Enterprise value | C10: =C6+C9
B11: Net cash | C11: =Assumptions!C21
B12: Equity value | C12: =C10+C11
B14: EV / FY27E revenue | C14: =C10/'P&L'!D6
B15: EV / FY27E EBITDA | C15: =C10/'P&L'!D12
B16: Terminal value share of EV | C16: =C9/C10
B18: Check: WACC > terminal growth | C18: =IF(Assumptions!C19>Assumptions!C20,"OK","ERROR")
